sphinxcontrib/doxylink/__init__.py
sphinxcontrib/doxylink/doxylink.py
sphinxcontrib/doxylink/parsing.py
sphinxcontrib_doxylink-1.13.0.dist-info/LICENSE
sphinxcontrib_doxylink-1.13.0.dist-info/METADATA
sphinxcontrib_doxylink-1.13.0.dist-info/WHEEL
sphinxcontrib_doxylink-1.13.0.dist-info/RECORD
