Metadata-Version: 2.3
Name: sphinxcontrib-doxylink
Version: 1.13.0
Summary: Sphinx extension for linking to Doxygen documentation.
License: BSD
Keywords: sphinx,doxygen,documentation,c++
Author: Matt Williams
Author-email: matt@milliams.com
Requires-Python: >=3.7,<4.0
Classifier: License :: Other/Proprietary License
Classifier: Programming Language :: Python :: 3
Classifier: Programming Language :: Python :: 3.7
Classifier: Programming Language :: Python :: 3.8
Classifier: Programming Language :: Python :: 3.9
Classifier: Programming Language :: Python :: 3.10
Classifier: Programming Language :: Python :: 3.11
Classifier: Programming Language :: Python :: 3.12
Classifier: Programming Language :: Python :: 3.13
Requires-Dist: Sphinx (>=1.6)
Requires-Dist: pyparsing (>=3.0.8,<4.0.0)
Requires-Dist: python-dateutil (>=2.8.2,<3.0.0)
Project-URL: Documentation, https://sphinxcontrib-doxylink.readthedocs.io
Project-URL: Repository, https://github.com/sphinx-contrib/doxylink
